wensleydale/__init__.py
wensleydale/cli.py
wensleydale/parser.py
wensleydale/test_cli.py
wensleydale/test_parser.py
wensleydale-0.1.0.dist-info/DESCRIPTION.rst
wensleydale-0.1.0.dist-info/METADATA
wensleydale-0.1.0.dist-info/RECORD
wensleydale-0.1.0.dist-info/WHEEL
wensleydale-0.1.0.dist-info/entry_points.txt
wensleydale-0.1.0.dist-info/metadata.json
wensleydale-0.1.0.dist-info/pbr.json
wensleydale-0.1.0.dist-info/top_level.txt
