Metadata-Version: 2.0
Name: wensleydale
Version: 0.1.0
Summary: Mr Wensleydale. Query the AST.
Home-page: https://github.com/RishiRamraj/wensleydale
Author: Rishi Ramraj
Author-email: thereisnocowlevel@gmail.com
License: UNKNOWN
Platform: UNKNOWN
Classifier: Development Status :: 2 - Pre-Alpha
Classifier: Environment :: Console
Classifier: Intended Audience :: Developers
Classifier: License :: OSI Approved :: MIT License
Classifier: Operating System :: POSIX :: Linux
Classifier: Programming Language :: Python :: 3.5
Requires-Dist: setuptools
Requires-Dist: pbr
Requires-Dist: click
